commitment/__init__.py
commitment/commitment.py
commitment-4.1.1.dist-info/METADATA
commitment-4.1.1.dist-info/WHEEL
commitment-4.1.1.dist-info/licenses/LICENSE
commitment-4.1.1.dist-info/RECORD
