Metadata-Version: 2.4
Name: commitment
Version: 4.1.1
Summary: An incomplete Python 3 wrapper for the GitHub API
License-Expression: MIT
License-File: LICENSE
Author: chris48s
Requires-Python: >=3.10
Classifier: Programming Language :: Python :: 3
Classifier: Programming Language :: Python :: 3.10
Classifier: Programming Language :: Python :: 3.11
Classifier: Programming Language :: Python :: 3.12
Classifier: Programming Language :: Python :: 3.13
Classifier: Programming Language :: Python :: 3.14
Requires-Dist: requests (==2.*)
Project-URL: Home, https://github.com/chris48s/commitment
Project-URL: Source, https://github.com/chris48s/commitment
